wsl_tools/__init__.py
wsl_tools/cached_property.py
wsl_tools/py.typed
wsl_tools-0.2.1.dist-info/LICENSE
wsl_tools-0.2.1.dist-info/WHEEL
wsl_tools-0.2.1.dist-info/METADATA
wsl_tools-0.2.1.dist-info/RECORD
